uiviewer/__init__.py
uiviewer/__main__.py
uiviewer/_device.py
uiviewer/_logger.py
uiviewer/_models.py
uiviewer/_utils.py
uiviewer/_version.py
uiviewer/cli.py
uiviewer/parser/__init.py
uiviewer/parser/android_hierarchy.py
uiviewer/parser/harmony_hierarchy.py
uiviewer/parser/ios_hierarchy.py
uiviewer/parser/utils.py
uiviewer/parser/xpath_lite.py
uiviewer/routers/__init__.py
uiviewer/routers/api.py
uiviewer/static/cdn/cdn.jsdelivr.net/npm/vue@2
uiviewer/static/cdn/code.jquery.com/jquery-3.6.0.min.js
uiviewer/static/cdn/unpkg.com/element-theme-dark@1.0.2/lib/fonts/element-icons.ttf
uiviewer/static/cdn/unpkg.com/element-theme-dark@1.0.2/lib/fonts/element-icons.woff
uiviewer/static/cdn/unpkg.com/element-theme-dark@1.0.2/lib/index.css
uiviewer/static/cdn/unpkg.com/element-ui/lib/index.js
uiviewer/static/css/style.css
uiviewer/static/favicon.ico
uiviewer/static/index.html
uiviewer/static/js/api.js
uiviewer/static/js/config.js
uiviewer/static/js/index.js
uiviewer/static/js/utils.js
uiviewer-1.1.6.dist-info/LICENSE
uiviewer-1.1.6.dist-info/METADATA
uiviewer-1.1.6.dist-info/WHEEL
uiviewer-1.1.6.dist-info/entry_points.txt
uiviewer-1.1.6.dist-info/RECORD
