Metadata-Version: 2.1
Name: uiviewer
Version: 1.1.6
Summary: UI hierarchy visualization tool, supporting Android, iOS, HarmonyOS NEXT.
License: MIT
Author: codematrixer
Author-email: chenli_gogo@163.com
Requires-Python: >=3.8,<4.0
Classifier: License :: OSI Approved :: MIT License
Classifier: Programming Language :: Python :: 3
Classifier: Programming Language :: Python :: 3.8
Classifier: Programming Language :: Python :: 3.9
Classifier: Programming Language :: Python :: 3.10
Classifier: Programming Language :: Python :: 3.11
Classifier: Programming Language :: Python :: 3.12
Classifier: Programming Language :: Python :: 3.13
Requires-Dist: aiofiles (>=23.1.0,<24.0.0)
Requires-Dist: facebook-wda (>=1.0.5,<2.0.0)
Requires-Dist: fastapi (>=0.68.0,<0.69.0)
Requires-Dist: hmdriver2 (>=1.4.0,<2.0.0)
Requires-Dist: tidevice (>=0.12.10,<0.13.0)
Requires-Dist: uiautomator2 (>=3.0.0,<4.0.0)
Requires-Dist: uvicorn (>=0.15.0,<0.16.0)
